firebolt_provider/__init__.py
firebolt_provider/example_dags/__init__.py
firebolt_provider/example_dags/example_firebolt.py
firebolt_provider/hooks/__init__.py
firebolt_provider/hooks/firebolt.py
firebolt_provider/operators/__init__.py
firebolt_provider/operators/firebolt.py
tests/__init__.py
tests/hooks/__init__.py
tests/hooks/test_firebolt.py
tests/operators/__init__.py
tests/operators/test_firebolt.py
tests/operators/test_start_stop.py
airflow_provider_firebolt-0.5.1.dist-info/LICENSE
airflow_provider_firebolt-0.5.1.dist-info/METADATA
airflow_provider_firebolt-0.5.1.dist-info/WHEEL
airflow_provider_firebolt-0.5.1.dist-info/entry_points.txt
airflow_provider_firebolt-0.5.1.dist-info/top_level.txt
airflow_provider_firebolt-0.5.1.dist-info/RECORD
