Metadata-Version: 2.1
Name: airflow_provider_firebolt
Version: 0.5.1
Summary: A Firebolt provider for Apache Airflow
Home-page: https://github.com/firebolt-db/airflow-provider-firebolt
Author: Firebolt
Author-email: support@firebolt.io
License: Apache-2.0
Project-URL: Bug Tracker, https://github.com/firebolt-db/airflow-provider-firebolt/issues
Classifier: License :: OSI Approved :: Apache Software License
Classifier: Operating System :: OS Independent
Classifier: Programming Language :: Python :: 3
Classifier: Programming Language :: Python :: 3 :: Only
Classifier: Programming Language :: Python :: 3.7
Classifier: Programming Language :: Python :: 3.8
Classifier: Programming Language :: Python :: 3.9
Requires-Python: >=3.7
License-File: LICENSE
Requires-Dist: apache-airflow >=1.10.0
Requires-Dist: firebolt-sdk >=1.8.0
Provides-Extra: dev
Requires-Dist: mypy ==1.* ; extra == 'dev'
Requires-Dist: pre-commit ==2.15.0 ; extra == 'dev'
Requires-Dist: pydantic ; extra == 'dev'
Requires-Dist: pytest ; extra == 'dev'
Requires-Dist: pytest-cov ; extra == 'dev'
Requires-Dist: pytest-mock ; extra == 'dev'
